README.md
setup.py
cheesefactory_logging/__init__.py
cheesefactory_logging/buffered_postgres_handler.py
cheesefactory_logging/multiprocess_handler.py
cheesefactory_logging.egg-info/PKG-INFO
cheesefactory_logging.egg-info/SOURCES.txt
cheesefactory_logging.egg-info/dependency_links.txt
cheesefactory_logging.egg-info/top_level.txt