Metadata-Version: 2.1
Name: cheesefactory-logging
Version: 0.2
Summary: Wrappers for the Python built-in logging package.
Home-page: https://bitbucket.org/hellsgrannies/cheesefactory-logging
Author: Todd Salazar
Author-email: unixsal@yahoo.com
License: UNKNOWN
Keywords: cheesefactory database logging postgresql postgres development
Platform: UNKNOWN
Classifier: Development Status :: 4 - Beta
Classifier: Intended Audience :: Developers
Classifier: License :: OSI Approved :: BSD License
Classifier: Programming Language :: Python :: 3.6
Classifier: Programming Language :: Python :: 3.7
Classifier: Programming Language :: Python :: 3.8
